ippython/__init__.py
ippython/ippython.py
ippython-0.0.2.dist-info/METADATA
ippython-0.0.2.dist-info/WHEEL
ippython-0.0.2.dist-info/top_level.txt
ippython-0.0.2.dist-info/RECORD
